kakaowork/__init__.py
kakaowork/__main__.py
kakaowork/blockkit.py
kakaowork/client.py
kakaowork/command.py
kakaowork/consts.py
kakaowork/exceptions.py
kakaowork/models.py
kakaowork/ratelimit.py
kakaowork/reactive.py
kakaowork/utils.py
kakaowork-0.8.0.dist-info/entry_points.txt
kakaowork-0.8.0.dist-info/LICENSE
kakaowork-0.8.0.dist-info/WHEEL
kakaowork-0.8.0.dist-info/METADATA
kakaowork-0.8.0.dist-info/RECORD
