Metadata-Version: 2.1
Name: kakaowork
Version: 0.8.0
Summary: Kakaowork Python client
Home-page: https://github.com/skyoo2003/kakaowork-py
License: MIT
Keywords: kakaowork
Author: Sung-Kyu Yoo
Author-email: skyoo2003@gmail.com
Requires-Python: >=3.7,<4.0
Classifier: License :: OSI Approved :: MIT License
Classifier: Programming Language :: Python :: 3
Classifier: Programming Language :: Python :: 3.10
Classifier: Programming Language :: Python :: 3.7
Classifier: Programming Language :: Python :: 3.8
Classifier: Programming Language :: Python :: 3.9
Provides-Extra: cli
Requires-Dist: aiosonic (>=0.10,<1)
Requires-Dist: click (>=7,<9); extra == "cli"
Requires-Dist: pydantic (>=1.6.2,<2)
Requires-Dist: pytz (>=2015.7)
Requires-Dist: urllib3 (>=1.14,<2)
Project-URL: Repository, https://github.com/skyoo2003/kakaowork-py
